randomless.py
randomless/__init__.py
randomless/base_random.py
randomless/main_random.py
randomless/randomless.py
randomless/entropy_sources/__init__.py
randomless/entropy_sources/base_entropy_source.py
randomless/entropy_sources/camera.py
randomless-0.1.8.dist-info/LICENSE.txt
randomless-0.1.8.dist-info/METADATA
randomless-0.1.8.dist-info/WHEEL
randomless-0.1.8.dist-info/top_level.txt
randomless-0.1.8.dist-info/RECORD
