Metadata-Version: 2.1
Name: randomless
Version: 0.1.8
Summary: A True Random Number Generator for python.
Home-page: https://github.com/artempavlov/randomless
Author: Artem Pavlov
License: UNKNOWN
Platform: UNKNOWN
Classifier: Programming Language :: Python :: 3 :: Only
Classifier: License :: OSI Approved :: GNU General Public License v3 (GPLv3)
Classifier: Operating System :: OS Independent
Requires-Python: >=3.4
Requires-Dist: opencv-python
Requires-Dist: numpy
